hume/__init__.py
hume/base_client.py
hume/client.py
hume/core/__init__.py
hume/core/api_error.py
hume/core/client_wrapper.py
hume/core/datetime_utils.py
hume/core/events.py
hume/core/file.py
hume/core/force_multipart.py
hume/core/http_client.py
hume/core/http_response.py
hume/core/jsonable_encoder.py
hume/core/pagination.py
hume/core/pydantic_utilities.py
hume/core/query_encoder.py
hume/core/remove_none_from_dict.py
hume/core/request_options.py
hume/core/serialization.py
hume/core/websocket.py
hume/empathic_voice/__init__.py
hume/empathic_voice/chat/__init__.py
hume/empathic_voice/chat/audio/asyncio_utilities.py
hume/empathic_voice/chat/audio/audio_utilities.py
hume/empathic_voice/chat/audio/chat_client.py
hume/empathic_voice/chat/audio/microphone.py
hume/empathic_voice/chat/audio/microphone_interface.py
hume/empathic_voice/chat/audio/microphone_sender.py
hume/empathic_voice/chat/client.py
hume/empathic_voice/chat/raw_client.py
hume/empathic_voice/chat/socket_client.py
hume/empathic_voice/chat/types/__init__.py
hume/empathic_voice/chat/types/publish_event.py
hume/empathic_voice/chat_groups/__init__.py
hume/empathic_voice/chat_groups/client.py
hume/empathic_voice/chat_groups/raw_client.py
hume/empathic_voice/chats/__init__.py
hume/empathic_voice/chats/client.py
hume/empathic_voice/chats/raw_client.py
hume/empathic_voice/client.py
hume/empathic_voice/configs/__init__.py
hume/empathic_voice/configs/client.py
hume/empathic_voice/configs/raw_client.py
hume/empathic_voice/control_plane/__init__.py
hume/empathic_voice/control_plane/client.py
hume/empathic_voice/control_plane/raw_client.py
hume/empathic_voice/control_plane/socket_client.py
hume/empathic_voice/errors/__init__.py
hume/empathic_voice/errors/bad_request_error.py
hume/empathic_voice/errors/unprocessable_entity_error.py
hume/empathic_voice/prompts/__init__.py
hume/empathic_voice/prompts/client.py
hume/empathic_voice/prompts/raw_client.py
hume/empathic_voice/raw_client.py
hume/empathic_voice/tools/__init__.py
hume-0.13.4.dist-info/LICENSE
hume-0.13.4.dist-info/METADATA
hume-0.13.4.dist-info/WHEEL
hume-0.13.4.dist-info/RECORD
