Metadata-Version: 2.1
Name: hume
Version: 0.13.4
Summary: A Python SDK for Hume AI
License: MIT
Keywords: hume,ai,evi,empathic,multimodal,expression,analysis,sentiment,voice,recognition,detection,emotion,interface,speech,audio,vision,expressive,embeddings,communication,learning
Requires-Python: >=3.9,<4
Classifier: Intended Audience :: Developers
Classifier: License :: OSI Approved :: MIT License
Classifier: Operating System :: MacOS
Classifier: Operating System :: Microsoft :: Windows
Classifier: Operating System :: OS Independent
Classifier: Operating System :: POSIX
Classifier: Operating System :: POSIX :: Linux
Classifier: Programming Language :: Python
Classifier: Programming Language :: Python :: 3
Classifier: Programming Language :: Python :: 3.9
Classifier: Programming Language :: Python :: 3.10
Classifier: Programming Language :: Python :: 3.11
Classifier: Programming Language :: Python :: 3.12
Classifier: Programming Language :: Python :: 3.8
Classifier: Topic :: Software Development :: Libraries :: Python Modules
Classifier: Typing :: Typed
Provides-Extra: examples
Provides-Extra: microphone
Requires-Dist: aiofiles (>=24.1.0,<25.0.0)
Requires-Dist: eval-type-backport (>=0.2.0,<0.3.0)
Requires-Dist: exceptiongroup (>=1.3.0,<2.0.0)
Requires-Dist: httpx (>=0.21.2)
Requires-Dist: jupyter (>=1.0.0,<2.0.0) ; extra == "examples"
Requires-Dist: pydantic (>=1.9.2)
Requires-Dist: pydantic-core (>=2.18.2)
Requires-Dist: sounddevice (>=0.4.6,<0.5.0) ; extra == "microphone"
Requires-Dist: typing_extensions (>=4.0.0)
Requires-Dist: websockets (>=13.1,<14.0)
